CHANGES.rst
DESCRIPTION.rst
LICENSE
MANIFEST.in
README.md
setup.py
src/wai.annotations.coqui.egg-info/PKG-INFO
src/wai.annotations.coqui.egg-info/SOURCES.txt
src/wai.annotations.coqui.egg-info/dependency_links.txt
src/wai.annotations.coqui.egg-info/entry_points.txt
src/wai.annotations.coqui.egg-info/namespace_packages.txt
src/wai.annotations.coqui.egg-info/requires.txt
src/wai.annotations.coqui.egg-info/top_level.txt
src/wai/annotations/coqui/__init__.py
src/wai/annotations/coqui/component/_CoquiSTTReader.py
src/wai/annotations/coqui/component/_CoquiSTTWriter.py
src/wai/annotations/coqui/component/_CoquiTTSReader.py
src/wai/annotations/coqui/component/_CoquiTTSWriter.py
src/wai/annotations/coqui/component/__init__.py
src/wai/annotations/coqui/specifier/_CoquiSTTInputFormatSpecifier.py
src/wai/annotations/coqui/specifier/_CoquiSTTOutputFormatSpecifier.py
src/wai/annotations/coqui/specifier/_CoquiTTSInputFormatSpecifier.py
src/wai/annotations/coqui/specifier/_CoquiTTSOutputFormatSpecifier.py
src/wai/annotations/coqui/specifier/__init__.py
src/wai/annotations/coqui/util/_CoquiSTTDialect.py
src/wai/annotations/coqui/util/_CoquiTTSDialect.py
src/wai/annotations/coqui/util/__init__.py
src/wai/annotations/coqui/util/_expected_header.py