Metadata-Version: 2.1
Name: wai.annotations.coqui
Version: 1.0.0
Summary: Module with plugins for managing datasets for coqui.ai TTS and STT.
Home-page: https://github.com/waikato-datamining/wai-annotations-coqui
Author: Peter Reutemann
Author-email: fracpete@waikato.ac.nz
License: Apache License Version 2.0
Classifier: Development Status :: 4 - Beta
Classifier: License :: OSI Approved :: Apache Software License
Classifier: Topic :: Scientific/Engineering :: Mathematics
Classifier: Programming Language :: Python :: 3
License-File: LICENSE
